dohproxy/__init__.py
dohproxy/client.py
dohproxy/client_protocol.py
dohproxy/constants.py
dohproxy/httpproxy.py
dohproxy/integration.py
dohproxy/protocol.py
dohproxy/proxy.py
dohproxy/server_protocol.py
dohproxy/stub.py
dohproxy/utils.py
doh_proxy-0.0.9.dist-info/LICENSE
doh_proxy-0.0.9.dist-info/METADATA
doh_proxy-0.0.9.dist-info/WHEEL
doh_proxy-0.0.9.dist-info/entry_points.txt
doh_proxy-0.0.9.dist-info/top_level.txt
doh_proxy-0.0.9.dist-info/RECORD
