Metadata-Version: 2.1
Name: doh-proxy
Version: 0.0.9
Summary: A client and proxy implementation of https://tools.ietf.org/html/draft-ietf-doh-dns-over-https-13
Home-page: https://github.com/facebookexperimental/doh-proxy
Author: Manu Bretelle
Author-email: chantra@fb.com
License: BSD
Keywords: doh proxy dns https
Platform: UNKNOWN
Classifier: Development Status :: 3 - Alpha
Classifier: Intended Audience :: Developers
Classifier: License :: OSI Approved :: BSD License
Classifier: Programming Language :: Python :: 3.5
Classifier: Programming Language :: Python :: 3.6
Classifier: Topic :: Internet :: Name Service (DNS)
Classifier: Topic :: Internet :: WWW/HTTP :: HTTP Servers
Classifier: Topic :: Security :: Cryptography
Classifier: Topic :: Utilities
Requires-Dist: aioh2 (>=0.2.1)
Requires-Dist: aiohttp (>=2.3.0)
Requires-Dist: dnspython
Requires-Dist: aiohttp-remotes (>=0.1.2)
Provides-Extra: integration_tests
Requires-Dist: colour-runner ; extra == 'integration_tests'
